omark/__init__.py
omark/files.py
omark/graphics.py
omark/omamer_species_placement.py
omark/omamer_utils.py
omark/omark.py
omark/scoring.py
omark/species_determination.py
omark/utils.py
omark/assets/summarized_report.txt
omark/assets/textual_report.txt
omark-0.3.1.data/scripts/omark
omark-0.3.1.dist-info/COPYING
omark-0.3.1.dist-info/COPYING.LESSER
omark-0.3.1.dist-info/LICENSE
omark-0.3.1.dist-info/METADATA
omark-0.3.1.dist-info/WHEEL
omark-0.3.1.dist-info/top_level.txt
omark-0.3.1.dist-info/RECORD
