Metadata-Version: 2.2
Name: omark
Version: 0.3.1
Summary: OMArk - Proteome quality assesment based on OMAmer placements
Home-page: https://github.com/DessimozLab/omark
Author: Yannis Nevers
Requires-Python: >=3.9
License-File: LICENSE
License-File: COPYING
License-File: COPYING.LESSER
Requires-Dist: biopython
Requires-Dist: ete3
Requires-Dist: omamer>=0.2.2
Requires-Dist: matplotlib
Requires-Dist: jinja2
Dynamic: author
Dynamic: description
Dynamic: description-content-type
Dynamic: home-page
Dynamic: requires-dist
Dynamic: requires-python
Dynamic: summary
